WeiXueyuanPythonJiaochengFix1/README.md
WeiXueyuanPythonJiaochengFix1/__init__.py
WeiXueyuanPythonJiaochengFix1/__main__.py
WeiXueyuanPythonJiaochengFix1/file.epub
WeiXueyuanPythonJiaochengFix1/index.html
WeiXueyuanPythonJiaochengFix1/css/__init__.py
WeiXueyuanPythonJiaochengFix1/css/annotations.css
WeiXueyuanPythonJiaochengFix1/css/main.css
WeiXueyuanPythonJiaochengFix1/css/normalize.css
WeiXueyuanPythonJiaochengFix1/css/popup.css
WeiXueyuanPythonJiaochengFix1/font/__init__.py
WeiXueyuanPythonJiaochengFix1/font/fontello.eot
WeiXueyuanPythonJiaochengFix1/font/fontello.svg
WeiXueyuanPythonJiaochengFix1/font/fontello.ttf
WeiXueyuanPythonJiaochengFix1/font/fontello.woff
WeiXueyuanPythonJiaochengFix1/img/__init__.py
WeiXueyuanPythonJiaochengFix1/img/annotator-glyph-sprite.png
WeiXueyuanPythonJiaochengFix1/img/annotator-icon-sprite.png
WeiXueyuanPythonJiaochengFix1/img/apple-touch-icon.png
WeiXueyuanPythonJiaochengFix1/img/cancelfullscreen.png
WeiXueyuanPythonJiaochengFix1/img/close.png
WeiXueyuanPythonJiaochengFix1/img/fullscreen.png
WeiXueyuanPythonJiaochengFix1/img/loader.gif
WeiXueyuanPythonJiaochengFix1/img/menu-icon.png
WeiXueyuanPythonJiaochengFix1/img/save.png
WeiXueyuanPythonJiaochengFix1/img/saved.png
WeiXueyuanPythonJiaochengFix1/img/settings-s.png
WeiXueyuanPythonJiaochengFix1/img/settings.png
WeiXueyuanPythonJiaochengFix1/img/star.png
WeiXueyuanPythonJiaochengFix1/js/__init__.py
WeiXueyuanPythonJiaochengFix1/js/epub.js
WeiXueyuanPythonJiaochengFix1/js/epub.min.js
WeiXueyuanPythonJiaochengFix1/js/epub.min.map
WeiXueyuanPythonJiaochengFix1/js/hooks.min.js
WeiXueyuanPythonJiaochengFix1/js/hooks.min.map
WeiXueyuanPythonJiaochengFix1/js/reader.js
WeiXueyuanPythonJiaochengFix1/js/reader.js.map
WeiXueyuanPythonJiaochengFix1/js/reader.min.js
WeiXueyuanPythonJiaochengFix1/js/reader.min.map
WeiXueyuanPythonJiaochengFix1/js/hooks/__init__.py
WeiXueyuanPythonJiaochengFix1/js/hooks/extensions/__init__.py
WeiXueyuanPythonJiaochengFix1/js/hooks/extensions/highlight.js
wei_xueyuan_python_jiaocheng_fix1-2025.3.25.0.dist-info/METADATA
wei_xueyuan_python_jiaocheng_fix1-2025.3.25.0.dist-info/WHEEL
wei_xueyuan_python_jiaocheng_fix1-2025.3.25.0.dist-info/entry_points.txt
wei_xueyuan_python_jiaocheng_fix1-2025.3.25.0.dist-info/top_level.txt
wei_xueyuan_python_jiaocheng_fix1-2025.3.25.0.dist-info/RECORD
